{"_id":{"$numberInt":"1"},"desc":"Testing","isDone":true,"_class":"com.assesment.Task.Utility.Tasks"}
{"_id":{"$numberInt":"2"},"desc":"buy medicine","isDone":true,"_class":"com.assesment.Task.Utility.Tasks"}
{"_id":{"$numberInt":"3"},"desc":"test3","isDone":true,"_class":"com.assesment.Task.Utility.Tasks"}
{"_id":{"$numberInt":"9"},"desc":"Make a call to mom","isDone":false,"_class":"com.assesment.Task.Utility.Tasks"}
{"_id":{"$numberInt":"11"},"desc":"task4","isDone":true,"_class":"com.assesment.Task.Utility.Tasks"}
{"_id":{"$numberInt":"13"},"desc":"task9","isDone":false,"_class":"com.assesment.Task.Utility.Tasks"}
{"_id":{"$numberInt":"21"},"desc":"send mail","isDone":false,"_class":"com.assesment.Task.Utility.Tasks"}
